gpt4all_code_review/__init__.py
gpt4all_code_review/gpt4all_code_review.py
gpt4all_code_review-2025.5.9.1718.dist-info/METADATA
gpt4all_code_review-2025.5.9.1718.dist-info/WHEEL
gpt4all_code_review-2025.5.9.1718.dist-info/entry_points.txt
gpt4all_code_review-2025.5.9.1718.dist-info/top_level.txt
gpt4all_code_review-2025.5.9.1718.dist-info/RECORD
