Metadata-Version: 2.4
Name: gpt4all-code-review
Version: 2025.5.9.1718
Summary: A self-contained tool for code review powered by GPT4ALL.
Home-page: https://github.com/chigwell/gpt4all-code-review
Author: Evgenii Evstafev
Author-email: chigwel@gmail.com
Requires-Dist: argparse
Requires-Dist: gpt4all
Requires-Dist: prettytable
Requires-Dist: datetime
Requires-Dist: console_progressbar
Dynamic: author
Dynamic: author-email
Dynamic: description
Dynamic: description-content-type
Dynamic: home-page
Dynamic: requires-dist
Dynamic: summary
